aioreloader/__init__.py
aioreloader/_contents.py
aioreloader-0.4.0.dist-info/LICENSE
aioreloader-0.4.0.dist-info/METADATA
aioreloader-0.4.0.dist-info/WHEEL
aioreloader-0.4.0.dist-info/top_level.txt
aioreloader-0.4.0.dist-info/RECORD
