Metadata-Version: 1.1
Name: aioreloader
Version: 0.4.0
Summary: Port of tornado reloader to asyncio
Home-page: https://github.com/and800/aioreloader
Author: Andriy Maletsky
Author-email: andriy.maletsky@gmail.com
License: MIT
Keywords: aiohttp asyncio
Platform: UNKNOWN
Classifier: Development Status :: 4 - Beta
Classifier: Intended Audience :: Developers
Classifier: License :: OSI Approved :: MIT License
Classifier: Operating System :: Microsoft :: Windows
Classifier: Operating System :: MacOS :: MacOS X
Classifier: Operating System :: POSIX :: Linux
Classifier: Programming Language :: Python :: 3.5
Classifier: Programming Language :: Python :: 3.6
Classifier: Programming Language :: Python :: 3.7
Classifier: Programming Language :: Python :: 3.8
Classifier: Programming Language :: Python :: 3.9
Classifier: Topic :: Software Development
